ical/__init__.py
ical/alarm.py
ical/calendar.py
ical/calendar_stream.py
ical/component.py
ical/diagnostics.py
ical/event.py
ical/exceptions.py
ical/freebusy.py
ical/iter.py
ical/journal.py
ical/list.py
ical/py.typed
ical/recur_adapter.py
ical/recurrence.py
ical/store.py
ical/timeline.py
ical/timespan.py
ical/timezone.py
ical/todo.py
ical/util.py
ical/compat/__init__.py
ical/compat/make_compat.py
ical/compat/timezone_compat.py
ical/parsing/__init__.py
ical/parsing/component.py
ical/parsing/const.py
ical/parsing/emoji.py
ical/parsing/property.py
ical/types/__init__.py
ical/types/boolean.py
ical/types/cal_address.py
ical/types/const.py
ical/types/data_types.py
ical/types/date.py
ical/types/date_time.py
ical/types/duration.py
ical/types/float.py
ical/types/geo.py
ical/types/integer.py
ical/types/parsing.py
ical/types/period.py
ical/types/priority.py
ical/types/recur.py
ical/types/relation.py
ical/types/request_status.py
ical/types/text.py
ical/types/uri.py
ical/types/utc_offset.py
ical/tzif/__init__.py
ical/tzif/extended_timezones.py
ical/tzif/model.py
ical/tzif/timezoneinfo.py
ical/tzif/tz_rule.py
ical/tzif/tzif.py
ical-12.1.3.dist-info/licenses/LICENSE
ical-12.1.3.dist-info/METADATA
ical-12.1.3.dist-info/WHEEL
ical-12.1.3.dist-info/top_level.txt
ical-12.1.3.dist-info/RECORD
