Metadata-Version: 2.4
Name: ical
Version: 12.1.3
Summary: Python iCalendar implementation (rfc 2445)
Author-email: Allen Porter <allen.porter@gmail.com>
License-Expression: Apache-2.0
Project-URL: Source, https://github.com/allenporter/ical
Requires-Python: >=3.13
License-File: LICENSE
Requires-Dist: python-dateutil>=2.8.2
Requires-Dist: tzdata>=2023.3
Requires-Dist: pydantic>=2.10.4
Dynamic: license-file
